daflsim-1.0.0.dev1.dist-info/METADATA
daflsim-1.0.0.dev1.dist-info/metadata.json
daflsim-1.0.0.dev1.dist-info/DESCRIPTION.rst
daflsim-1.0.0.dev1.dist-info/top_level.txt
daflsim-1.0.0.dev1.dist-info/RECORD
daflsim-1.0.0.dev1.dist-info/entry_points.txt
daflsim-1.0.0.dev1.dist-info/WHEEL
daflsim/daflsim.py
daflsim/literate.py
daflsim/queue_matrix.py
daflsim/defaultCfg.py
daflsim/__init__.py
daflsim/actions.py
daflsim/cron.py
