Metadata-Version: 2.0
Name: daflsim
Version: 1.0.0.dev1
Summary: Simulate a data-flow described by a graphviz diagram
Home-page: https://github.com/pothiers/daflsim
Author: S. Pothier
Author-email: pothier@noao.com
License: MIT
Keywords: simulation network graph data-flow
Platform: UNKNOWN
Classifier: Development Status :: 3 - Alpha
Classifier: Intended Audience :: Developers
Classifier: Intended Audience :: Information Technology
Classifier: Intended Audience :: Science/Research
Classifier: Intended Audience :: System Administrators
Classifier: Intended Audience :: Telecommunications Industry
Classifier: Topic :: Scientific/Engineering :: Astronomy
Classifier: Topic :: Software Development :: Code Generators
Classifier: License :: OSI Approved :: MIT License
Classifier: Programming Language :: Python :: 3.3
Classifier: Programming Language :: Python :: 3.4
Requires-Dist: graphviz
Requires-Dist: networkx
Requires-Dist: simpy (>=3)
